odoo/addons/ssi_fleet_management/README.rst
odoo/addons/ssi_fleet_management/__init__.py
odoo/addons/ssi_fleet_management/__manifest__.py
odoo/addons/ssi_fleet_management/menu.xml
odoo/addons/ssi_fleet_management/models/__init__.py
odoo/addons/ssi_fleet_management/models/fleet_vehicle.py
odoo/addons/ssi_fleet_management/models/res_company.py
odoo/addons/ssi_fleet_management/models/res_config_settings.py
odoo/addons/ssi_fleet_management/security/ir.model.access.csv
odoo/addons/ssi_fleet_management/security/ir_module_category_data.xml
odoo/addons/ssi_fleet_management/security/res_group_data.xml
odoo/addons/ssi_fleet_management/static/description/icon.png
odoo/addons/ssi_fleet_management/views/fleet_vehicle_views.xml
odoo/addons/ssi_fleet_management/views/res_config_settings_views.xml
odoo14_addon_ssi_fleet_management-14.0.2.1.0.dist-info/METADATA
odoo14_addon_ssi_fleet_management-14.0.2.1.0.dist-info/WHEEL
odoo14_addon_ssi_fleet_management-14.0.2.1.0.dist-info/top_level.txt
odoo14_addon_ssi_fleet_management-14.0.2.1.0.dist-info/RECORD
